setup.py
cakey.egg-info/PKG-INFO
cakey.egg-info/SOURCES.txt
cakey.egg-info/dependency_links.txt
cakey.egg-info/not-zip-safe
cakey.egg-info/top_level.txt
cobtc/__init__.py