Metadata-Version: 1.0
Name: cakey
Version: 0.1
Summary: scraping bitcoin values
Home-page: https://www.github.com/Alvixeon/btc-py
Author: Alvixeon
Author-email: remusername@gmail.com
License: MIT
Platform: UNKNOWN
